{
    "code":200,
    "data":{
        "logs":[
            {
                "opStatus":"主管审批",
                "operator":"梅长苏",
                "opResult":"同意",
                "opTime":"2019-11-11 00:30"
            },
            {
                "opStatus":"HRG",
                "operator":"Tony",
                "opResult":"同意",
                "opTime":"2019-11-11 01:31"
            },
            {
                "opStatus":"C&amp;B审核人",
                "operator":"CC",
                "opResult":"同意",
                "opTime":"2019-11-11 02:32"
            },
            {
                "opStatus":"业务线审批",
                "operator":"玛丽",
                "opResult":"同意",
                "opTime":"2019-11-11 03:33"
            },
            {
                "opStatus":"HR线审批",
                "operator":"宋江",
                "opResult":"同意",
                "opTime":"2019-11-11 04:34"
            }
        ],
        "person":{
            "avatar":"//aliwork.alicdn.com/tfscom/T1fxt7FtJlXXXXXXXX_40x40",
            "surname":"郭",
            "name":"嘻嘻",
            "phone":"13812345678",
            "email":"chinaNo1@aliwork-inc.com",
            "region":"中国/浙江",
            "address":"杭州",
            "workTime":"大三",
            "education":"五道口职业技术学院",
            "position":"党支书",
            "college":"计算机学院",
            "workAddress":"杭州"
        },
        "preJobs":[
            {
                "id":1,
                "time":"2020.01-2020.05",
                "company":"浙江杭州天猫有限公司",
                "bu":"基础服务事业部",
                "position":"产品",
                "address":"中国/浙江",
                "description":"Fusion 是一套企业级中后台设计系统解决方案，致力于解决产品体验一致性问题、设计研发协同问题，以及UI开发效率问题。"
            },
            {
                "id":2,
                "time":"2019.10-2020.12",
                "company":"蚂蚁金服",
                "bu":"企业服务事业部",
                "position":"产品",
                "address":"中国/浙江",
                "description":"Antd 是一套企业级中后台设计系统解决方案，致力于解决产品体验一致性问题、设计研发协同问题，以及UI开发效率问题。"
            }
        ],
        "achievement":{
            "gPoint":4.2,
            "scholarship":"省级优秀",
            "match":"acm金牌"
        },
        "dataLabelLine":[
            {
                "name":"javascript",
                "population":41.8
            },
            {
                "name":"html",
                "population":38
            },
            {
                "name":"css",
                "population":33.7
            },
            {
                "name":"css3",
                "population":30.7
            },
            {
                "name":"html5",
                "population":25.8
            },
            {
                "name":"vue",
                "population":31.7
            },
            {
                "name":"react",
                "population":33
            },
            {
                "name":"angular",
                "population":46
            },
            {
                "name":"nodejs",
                "population":38.3
            },
            {
                "name":"less",
                "population":28
            },
            {
                "name":"threejs",
                "population":42.5
            },
            {
                "name":"d3js",
                "population":30.3
            }
        ]
    },
    "msg":"ok"
}